http_monitor/__init__.py
http_monitor/middleware.py
http_monitor/models.py
http_monitor/urls.py
http_monitor/views.py
http_monitor/with_mixin_middleware.py
tests/__init__.py
tests/test_settings.py
django_http_monitor-0.5.5.dist-info/METADATA
django_http_monitor-0.5.5.dist-info/WHEEL
django_http_monitor-0.5.5.dist-info/top_level.txt
django_http_monitor-0.5.5.dist-info/RECORD
