Metadata-Version: 1.1
Name: django-http-monitor
Version: 0.5.5
Summary: Django http monitor is a Django app for record http request and response in debug.
Home-page: https://github.com/ZhangBohan/django-http-monitor
Author: Bohan
Author-email: me@bohanzhang.com
License: BSD License
Platform: UNKNOWN
Classifier: Environment :: Web Environment
Classifier: Framework :: Django
Classifier: Framework :: Django :: 1.8
Classifier: Intended Audience :: Developers
Classifier: License :: OSI Approved :: BSD License
Classifier: Operating System :: OS Independent
Classifier: Programming Language :: Python
Classifier: Programming Language :: Python :: 2
Classifier: Programming Language :: Python :: 3
Classifier: Topic :: Internet :: WWW/HTTP
Classifier: Topic :: Internet :: WWW/HTTP :: Dynamic Content
